foliant/backends/docus/__init__.py
foliant/backends/docus/docus.py
foliant/backends/docus/index.py
foliant/backends/docus/sidebars.py
foliant/backends/docus/assets/Footer.js
foliant/backends/docus/assets/siteConfig.js
foliant/preprocessors/docus.py
foliantcontrib.docus-0.2.0.dist-info/LICENSE
foliantcontrib.docus-0.2.0.dist-info/METADATA
foliantcontrib.docus-0.2.0.dist-info/WHEEL
foliantcontrib.docus-0.2.0.dist-info/top_level.txt
foliantcontrib.docus-0.2.0.dist-info/RECORD
